MANIFEST.in
README.rst
setup.py
examples/compute_pi_client.py
examples/compute_pi_server.py
examples/tx_rpc_client.py
examples/tx_rpc_client_ssl.py
examples/tx_rpc_client_udp.py
examples/tx_rpc_client_udp_multicast.py
examples/tx_rpc_client_unix.py
examples/tx_rpc_server.py
examples/tx_rpc_server_ssl.py
examples/tx_rpc_server_udp.py
examples/tx_rpc_server_udp_multicast.py
examples/tx_rpc_server_unix.py
txmsgpackrpc/__init__.py
txmsgpackrpc/client.py
txmsgpackrpc/constant.py
txmsgpackrpc/error.py
txmsgpackrpc/factory.py
txmsgpackrpc/handler.py
txmsgpackrpc/mixin.py
txmsgpackrpc/protocol.py
txmsgpackrpc/server.py
txmsgpackrpc.egg-info/PKG-INFO
txmsgpackrpc.egg-info/SOURCES.txt
txmsgpackrpc.egg-info/dependency_links.txt
txmsgpackrpc.egg-info/requires.txt
txmsgpackrpc.egg-info/top_level.txt