Metadata-Version: 1.1
Name: txmsgpackrpc
Version: 1.2
Summary: txmsgpackrpc is a Twisted library to support msgpack-rpc
Home-page: https://github.com/jakm/txmsgpackrpc
Author: Jakub Matys
Author-email: matys.jakub@gmail.com
License: MIT
Keywords: twisted msgpack rpc
Platform: UNKNOWN
Classifier: Development Status :: 4 - Beta
Classifier: Framework :: Twisted
Classifier: Intended Audience :: Developers
Classifier: License :: OSI Approved :: MIT License
Classifier: Operating System :: OS Independent
Classifier: Programming Language :: Python
Classifier: Programming Language :: Python :: 2.7
Classifier: Programming Language :: Python :: 3.3
Classifier: Programming Language :: Python :: 3.4
Classifier: Programming Language :: Python :: 3.5
Classifier: Programming Language :: Python :: Implementation :: CPython
Classifier: Topic :: Software Development :: Libraries :: Python Modules
